libpresign-1.2.0.dist-info/RECORD
libpresign-1.2.0.dist-info/WHEEL
libpresign-1.2.0.dist-info/METADATA
libpresign/_version.pyi
libpresign/_version.py
libpresign/__init__.py
libpresign/libpresign.so
libpresign/libpresign.pyi
libpresign/py.typed
libpresign/.dylibs/libcrypto.3.dylib
