Metadata-Version: 2.2
Name: libpresign
Version: 1.2.0
Summary: High-performance library for generating AWS S3 presigned URLs
Keywords: aws,s3,presigned-url,performance,c++
Author-Email: Mykola Bashmakov <mykola@bashmakov.agency>
License: MIT
Classifier: Development Status :: 5 - Production/Stable
Classifier: Intended Audience :: Developers
Classifier: License :: OSI Approved :: MIT License
Classifier: Programming Language :: Python :: 3
Classifier: Programming Language :: Python :: 3.8
Classifier: Programming Language :: Python :: 3.9
Classifier: Programming Language :: Python :: 3.10
Classifier: Programming Language :: Python :: 3.11
Classifier: Programming Language :: Python :: 3.12
Classifier: Programming Language :: Python :: 3.13
Classifier: Programming Language :: C++
Classifier: Operating System :: OS Independent
Classifier: Topic :: Software Development :: Libraries :: Python Modules
Project-URL: Homepage, https://github.com/myk0la-b/libpresign
Project-URL: Documentation, https://myk0la-b.github.io/libpresign/
Project-URL: Repository, https://github.com/myk0la-b/libpresign.git
Project-URL: Issues, https://github.com/myk0la-b/libpresign/issues
Project-URL: Changelog, https://github.com/myk0la-b/libpresign/blob/main/CHANGELOG.md
Requires-Python: >=3.8
Provides-Extra: test
Requires-Dist: pytest>=7.0; extra == "test"
Requires-Dist: pytest-cov>=4.0; extra == "test"
Requires-Dist: pytest-benchmark>=4.0; extra == "test"
Requires-Dist: boto3>=1.26.0; extra == "test"
Requires-Dist: psutil>=5.9.0; extra == "test"
Requires-Dist: numpy>=1.21.0; extra == "test"
Provides-Extra: dev
Requires-Dist: pytest>=7.0; extra == "dev"
Requires-Dist: pytest-cov>=4.0; extra == "dev"
Requires-Dist: pytest-benchmark>=4.0; extra == "dev"
Requires-Dist: boto3>=1.26.0; extra == "dev"
Requires-Dist: psutil>=5.9.0; extra == "dev"
Requires-Dist: numpy>=1.21.0; extra == "dev"
Requires-Dist: ruff>=0.1.0; extra == "dev"
Requires-Dist: mypy>=1.0; extra == "dev"
Requires-Dist: build>=1.0; extra == "dev"
Requires-Dist: twine>=4.0; extra == "dev"
Requires-Dist: cibuildwheel>=2.16; extra == "dev"
Requires-Dist: python-semantic-release>=8.0; extra == "dev"
Requires-Dist: mkdocs>=1.5; extra == "dev"
Requires-Dist: mkdocs-material>=9.4; extra == "dev"
Requires-Dist: mkdocstrings[python]>=0.24; extra == "dev"
Provides-Extra: docs
Requires-Dist: mkdocs>=1.5; extra == "docs"
Requires-Dist: mkdocs-material>=9.4; extra == "docs"
Requires-Dist: mkdocstrings[python]>=0.24; extra == "docs"
Requires-Dist: markdown>=3.4; extra == "docs"
